README.md
setup.py
gitPkgManager/__init__.py
gitPkgManager/pkgManager.py
python_git_pkgManager.egg-info/PKG-INFO
python_git_pkgManager.egg-info/SOURCES.txt
python_git_pkgManager.egg-info/dependency_links.txt
python_git_pkgManager.egg-info/not-zip-safe
python_git_pkgManager.egg-info/requires.txt
python_git_pkgManager.egg-info/top_level.txt