Metadata-Version: 1.1
Name: python-git-pkgManager
Version: 0.511
Summary: Import extension from github directly into your project.
Home-page: https://github.com/bennyelg/git_import
Author: Benny Elgazar
Author-email: elgazarbenny@gmail.com
License: MIT
Platform: any
Classifier: Intended Audience :: Developers
Classifier: Operating System :: MacOS :: MacOS X
Classifier: Operating System :: Unix
Classifier: Operating System :: POSIX
Classifier: Programming Language :: Python
Classifier: Programming Language :: Python :: 3.6
Classifier: Topic :: Software Development
Classifier: Topic :: Software Development :: Libraries
Classifier: Topic :: Software Development :: Libraries :: Python Modules
Classifier: Topic :: Utilities
